sliw_1/SLIW.py
sliw_1/__init__.py
SLIW-0.0.5.dist-info/METADATA
SLIW-0.0.5.dist-info/WHEEL
SLIW-0.0.5.dist-info/top_level.txt
SLIW-0.0.5.dist-info/RECORD
